{"notes":[{"timestamp":"2/25/2023","content":"Just something to talk on here, example1"},{"timestamp":"2/25/2023 9:18:39 PM","content":"Just something to talk on here, example2"},{"timestamp":"2/27/2023 7:10:23 PM","content":"What is this, does dsafesadsafdsathis work"},{"timestamp":"2/27/2023 7:11:01 PM","content":"What is this, does this work"},{"timestamp":"2/27/2023 7:12:14 PM","content":"Another example to see if this works the way i want it to"},{"timestamp":"2/27/2023 7:25:59 PM","content":"Let us see if this is what it does what i need"},{"timestamp":"2/27/2023 7:30:59 PM","content":"Let us see if this is what it does what i need"},{"timestamp":"2/27/2023 7:32:41 PM","content":"I am hoping this is what I need now!"},{"timestamp":"2/27/2023 7:32:56 PM","content":"I am hoping this is what I need now!"},{"timestamp":"2/27/2023 7:33:32 PM","content":"I am hoping this is what I need and I will now celebrate!"},{"timestamp":"2/27/2023 7:54:02 PM","content":"does this work the way I want it to"},{"timestamp":"2/27/2023 7:56:09 PM","content":"does this work the way I want it to"}]}